setup.py
coin_data/__init__.py
coin_data/base.py
coin_data/coin_market_map.py
coin_data/factory.py
coin_data.egg-info/PKG-INFO
coin_data.egg-info/SOURCES.txt
coin_data.egg-info/dependency_links.txt
coin_data.egg-info/requires.txt
coin_data.egg-info/top_level.txt
coin_data/tests/__init__.py
coin_data/tests/test_coin_market_map.py