Metadata-Version: 1.0
Name: coin-data
Version: 0.1.4
Summary: 获取各种加密货币的价格数据
Home-page: https://github.com/Jay54520/coin_data
Author: UNKNOWN
Author-email: UNKNOWN
License: UNKNOWN
Platform: any
